portale/__init__.py
portale-0.9.91.dist-info/licenses/LICENSE
portale-0.9.91.dist-info/METADATA
portale-0.9.91.dist-info/WHEEL
portale-0.9.91.dist-info/top_level.txt
portale-0.9.91.dist-info/RECORD
