Metadata-Version: 2.4
Name: portale
Version: 0.9.91
Summary: Requests based HTTP/REST API client with flexible cache support
Author-email: Shekhar Tiwatne <pythonic@gmail.com>
License: MIT License
Project-URL: Homepage, http://pypi.python.org/pypi/portale/
Classifier: Programming Language :: Python :: 3
License-File: LICENSE
Requires-Dist: requests
Requires-Dist: walrus
Provides-Extra: pyreqwest
Requires-Dist: pyreqwest; extra == "pyreqwest"
Dynamic: license-file
